{"variables":[],"info":{"name":"","_postman_id":"fff21208-cd25-4967-889d-ba159d572abb","description":"","schema":"https:\/\/schema.getpostman.com\/json\/collection\/v2.0.0\/collection.json"},"item":[{"name":"Events\n\nController for event related operations","description":"","item":[{"name":"List all Events","request":{"url":"http:\/\/localhost\/api\/events","method":"GET","body":{"mode":"formdata","formdata":[]},"description":"Lists all events in the database","response":[]}},{"name":"Event Insert","request":{"url":"http:\/\/localhost\/api\/events","method":"POST","body":{"mode":"formdata","formdata":[]},"description":"Inserts an event in the database","response":[]}},{"name":"Event Detail","request":{"url":"http:\/\/localhost\/api\/events\/{event}","method":"GET","body":{"mode":"formdata","formdata":[]},"description":"Gives the details of a event","response":[]}},{"name":"Event Update","request":{"url":"http:\/\/localhost\/api\/events\/{event}","method":"PUT","body":{"mode":"formdata","formdata":[]},"description":"Update an event in the database","response":[]}},{"name":"Delete Event","request":{"url":"http:\/\/localhost\/api\/events\/{event}","method":"DELETE","body":{"mode":"formdata","formdata":[]},"description":"Deletes an event in the database","response":[]}},{"name":"Users of a Event","request":{"url":"http:\/\/localhost\/api\/events\/{event}\/users","method":"GET","body":{"mode":"formdata","formdata":[]},"description":"Returns the users linked to an event","response":[]}}]},{"name":"Family\n\nController for family related operations","description":"","item":[{"name":"List all Families","request":{"url":"http:\/\/localhost\/api\/family","method":"GET","body":{"mode":"formdata","formdata":[]},"description":"Lists all families in the database","response":[]}},{"name":"Family Insert","request":{"url":"http:\/\/localhost\/api\/family","method":"POST","body":{"mode":"formdata","formdata":[]},"description":"Inserts a family in the database","response":[]}},{"name":"Family Detail","request":{"url":"http:\/\/localhost\/api\/family\/{family}","method":"GET","body":{"mode":"formdata","formdata":[]},"description":"Gives the details of a family","response":[]}},{"name":"Family Update","request":{"url":"http:\/\/localhost\/api\/family\/{family}","method":"PUT","body":{"mode":"formdata","formdata":[]},"description":"Update a family in the database","response":[]}},{"name":"Delete Family","request":{"url":"http:\/\/localhost\/api\/family\/{family}","method":"DELETE","body":{"mode":"formdata","formdata":[]},"description":"Deletes a family in the database","response":[]}},{"name":"Get Family Users","request":{"url":"http:\/\/localhost\/api\/family\/{family}\/users","method":"GET","body":{"mode":"formdata","formdata":[]},"description":"Lists the users of a Family","response":[]}}]},{"name":"Lists\n\nController for shopping lists related operations","description":"","item":[{"name":"List all Lists","request":{"url":"http:\/\/localhost\/api\/lists","method":"GET","body":{"mode":"formdata","formdata":[]},"description":"Lists all lists in the database","response":[]}},{"name":"List Insert","request":{"url":"http:\/\/localhost\/api\/lists","method":"POST","body":{"mode":"formdata","formdata":[]},"description":"Inserts a list in the database","response":[]}},{"name":"List Detail","request":{"url":"http:\/\/localhost\/api\/lists\/{list}","method":"GET","body":{"mode":"formdata","formdata":[]},"description":"Gives the details of a list","response":[]}},{"name":"List Update","request":{"url":"http:\/\/localhost\/api\/lists\/{list}","method":"PUT","body":{"mode":"formdata","formdata":[]},"description":"Update a list in the database","response":[]}},{"name":"Delete List","request":{"url":"http:\/\/localhost\/api\/lists\/{list}","method":"DELETE","body":{"mode":"formdata","formdata":[]},"description":"Deletes a list in the database","response":[]}},{"name":"Users of a List","request":{"url":"http:\/\/localhost\/api\/lists\/{list}\/users","method":"GET","body":{"mode":"formdata","formdata":[]},"description":"Returns the users linked to a list","response":[]}},{"name":"Get List Products","request":{"url":"http:\/\/localhost\/api\/lists\/{list}\/products","method":"GET","body":{"mode":"formdata","formdata":[]},"description":"Shows the users of a list","response":[]}}]},{"name":"Produtos\n\nM\u00e9todo geral para controla produtos","description":"","item":[{"name":"List All Products","request":{"url":"http:\/\/localhost\/api\/products","method":"GET","body":{"mode":"formdata","formdata":[]},"description":"Lists all products in the database","response":[]}},{"name":"Product Insert","request":{"url":"http:\/\/localhost\/api\/products","method":"POST","body":{"mode":"formdata","formdata":[]},"description":"Inserts a product in the database","response":[]}},{"name":"Products Detail","request":{"url":"http:\/\/localhost\/api\/products\/{product}","method":"GET","body":{"mode":"formdata","formdata":[]},"description":"Shows the details of a product","response":[]}},{"name":"Product Update","request":{"url":"http:\/\/localhost\/api\/products\/{product}","method":"PUT","body":{"mode":"formdata","formdata":[]},"description":"Updates a product in the database","response":[]}},{"name":"Product Delete","request":{"url":"http:\/\/localhost\/api\/products\/{product}","method":"DELETE","body":{"mode":"formdata","formdata":[]},"description":"Deletes a product in the database","response":[]}}]},{"name":"Users\n\nController for user related operations","description":"","item":[{"name":"List all Users","request":{"url":"http:\/\/localhost\/api\/users","method":"GET","body":{"mode":"formdata","formdata":[]},"description":"Lists all users in the database","response":[]}},{"name":"User Insert","request":{"url":"http:\/\/localhost\/api\/users","method":"POST","body":{"mode":"formdata","formdata":[]},"description":"Inserts a user in the database","response":[]}},{"name":"User Detail","request":{"url":"http:\/\/localhost\/api\/users\/{user}","method":"GET","body":{"mode":"formdata","formdata":[]},"description":"Gives the details of a user","response":[]}},{"name":"User Update","request":{"url":"http:\/\/localhost\/api\/users\/{user}","method":"PUT","body":{"mode":"formdata","formdata":[]},"description":"Update a family in the database","response":[]}},{"name":"Delete User","request":{"url":"http:\/\/localhost\/api\/users\/{user}","method":"DELETE","body":{"mode":"formdata","formdata":[]},"description":"Deletes a user in the database","response":[]}},{"name":"Authenticate User","request":{"url":"http:\/\/localhost\/api\/user","method":"GET","body":{"mode":"formdata","formdata":[]},"description":"Authenticate a user in the database","response":[]}}]}]}